ntmirror/__init__.py
ntmirror/dbloader_mysql.py
ntmirror/dbloader_sqlalchemy.py
ntmirror/dbloader_sqlwriter.py
ntmirror/dbschema.py
ntmirror/scripts_helper.py
ntmirror-1.4.1.data/scripts/ntmirror-dbload
ntmirror-1.4.1.data/scripts/ntmirror-extract-subtree
ntmirror-1.4.1.dist-info/AUTHORS.txt
ntmirror-1.4.1.dist-info/LICENSE.txt
ntmirror-1.4.1.dist-info/METADATA
ntmirror-1.4.1.dist-info/WHEEL
ntmirror-1.4.1.dist-info/top_level.txt
ntmirror-1.4.1.dist-info/RECORD
