Metadata-Version: 2.1
Name: ntmirror
Version: 1.4.1
Summary: Easily updatable local NCBI taxonomy database copy
Home-page: https://github.com/ggonnella/fastsubtrees/tree/main/ntmirror
Author: Giorgio Gonnella
Author-email: gonnella@zbh.uni-hamburg.de
License: ISC
Keywords: ncbi taxonomy database mirror
Platform: UNKNOWN
Classifier: Development Status :: 5 - Production/Stable
Classifier: Environment :: Console
Classifier: Intended Audience :: Developers
Classifier: Intended Audience :: End Users/Desktop
Classifier: Intended Audience :: Science/Research
Classifier: License :: OSI Approved :: ISC License (ISCL)
Classifier: Operating System :: MacOS :: MacOS X
Classifier: Operating System :: POSIX :: Linux
Classifier: Programming Language :: Python :: 3 :: Only
Classifier: Topic :: Software Development :: Libraries
License-File: LICENSE.txt
License-File: AUTHORS.txt
Requires-Dist: sqlalchemy
Requires-Dist: sqlalchemy-repr
Requires-Dist: mysql
Requires-Dist: mariadb
Requires-Dist: loguru
Requires-Dist: snacli
Requires-Dist: schema
Requires-Dist: ntdownload
